AUTHORS.txt
LICENSE.txt
MANIFEST.in
README.md
setup.py
test.py
queue_front/__init__.py
queue_front.egg-info/PKG-INFO
queue_front.egg-info/SOURCES.txt
queue_front.egg-info/dependency_links.txt
queue_front.egg-info/top_level.txt
queue_front/backends/__init__.py
queue_front/backends/base.py
queue_front/backends/beanstalkd.py
queue_front/backends/dummy.py
queue_front/backends/memcached.py
queue_front/backends/redisd.py
queue_front/backends/sqs.py