Metadata-Version: 1.1
Name: queue-front
Version: 0.7.2
Summary: A lowest-common-denominator API for interacting with lightweight queues. A fork of https://code.google.com/p/queues/.
Home-page: https://bitbucket.org/dwaiter/queue-front
Author: Dwaiter.com
Author-email: dev@dwaiter.com
License: UNKNOWN
Platform: UNKNOWN
Classifier: Development Status :: 5 - Production/Stable
Classifier: Environment :: Web Environment
Classifier: Intended Audience :: Developers
Classifier: License :: OSI Approved :: MIT License
Classifier: Natural Language :: English
Classifier: Operating System :: OS Independent
Classifier: Programming Language :: Python
Classifier: Programming Language :: Python :: 2
Classifier: Programming Language :: Python :: 2.6
Classifier: Programming Language :: Python :: 2.7
Classifier: Programming Language :: Python :: 3
Classifier: Programming Language :: Python :: 3.2
Classifier: Programming Language :: Python :: 3.3
Classifier: Topic :: Utilities
Classifier: Framework :: Django
